flask_login_oidc/__init__.py
flask_login_oidc/client.py
flask_login_oidc/user.py
flask_login_oidc-1.0.2.dist-info/LICENSE
flask_login_oidc-1.0.2.dist-info/METADATA
flask_login_oidc-1.0.2.dist-info/WHEEL
flask_login_oidc-1.0.2.dist-info/top_level.txt
flask_login_oidc-1.0.2.dist-info/RECORD
