Metadata-Version: 2.1
Name: flask-login-oidc
Version: 1.0.2
Summary: Flask OpenID with flask-login
Author-email: Frédérick NEY <frederick.ney@gmail.com>
License:                     GNU GENERAL PUBLIC LICENSE
Project-URL: Homepage, https://github.com/frederickney/flask-login-oidc
Project-URL: Documentation, https://github.com/frederickney/flask-login-oidc/blob/master/README.md
Project-URL: Repository, https://github.com/frederickney/flask-login-oidc
Project-URL: Issues, https://github.com/frederickney/flask-login-oidc/issues
Project-URL: source, https://github.com/frederickney/flask-login-oidc
Classifier: Environment :: Web Environment
Classifier: Intended Audience :: Developers
Classifier: Operating System :: OS Independent
Classifier: Framework :: Flask
Classifier: Topic :: Software Development :: Libraries :: Python Modules
Classifier: Programming Language :: Python :: 3.7
Classifier: Programming Language :: Python :: 3.8
Classifier: Programming Language :: Python :: 3.9
Classifier: Programming Language :: Python :: 3.10
Classifier: Programming Language :: Python :: 3.11
Classifier: Programming Language :: Python :: 3.12
Classifier: Programming Language :: Python :: 3.13
Requires-Python: >=3.7
License-File: LICENSE
Requires-Dist: authlib
Requires-Dist: requests
Requires-Dist: Flask-Login
Requires-Dist: Flask
Requires-Dist: importlib-metadata; python_version > "3.7"
